{
  "name": "Featherstar Repo",
  "identifier": "pidev.feather.testing",
  "iconURL": "https://ratsknarp.github.io/featherstar/featherpurp.png",
  "apps": [
{
    "name": "iFeather",
    "bundleIdentifier": "thewonderofyou.Feather-idevice",
    "developerName": "Samara",
    "version": "testthree",
    "versionDate": "2025-05-12T20:50:32Z",
    "downloadURL": "https://ratsknarp.github.io/featherstar/Feather-idevice.ipa",
    "iconURL": "https://ratsknarp.github.io/featherstar/featherpurp.png",
    "localizedDescription": "Personal build of Feather with idevice.",
    "subtitle": "Feather (idevice)",
    "tintColor": "0033cc",
    "size": 0
  }
]}
